biodblinker/__init__.py
biodblinker/config.py
biodblinker/dblink.py
biodblinker/fileio.py
biodblinker/mapping_generator.py
biodblinker/sources.ini
biodblinker-0.0.4.dist-info/LICENSE
biodblinker-0.0.4.dist-info/METADATA
biodblinker-0.0.4.dist-info/WHEEL
biodblinker-0.0.4.dist-info/top_level.txt
biodblinker-0.0.4.dist-info/RECORD
