Metadata-Version: 2.1
Name: biodblinker
Version: 0.0.4
Summary: A library for linking entities of biological knowledge bases.
Home-page: https://github.com/dsi-bdi/biodblinker
Author: INSIGHT Centre for Data Analytics
Author-email: sameh.kamal@insight-centre.org
License: UNKNOWN
Platform: UNKNOWN
Requires-Python: >=3.6
Requires-Dist: tqdm
Requires-Dist: requests
Requires-Dist: packaging
